quad_sim_python/__init__.py
quad_sim_python/ctrl.py
quad_sim_python/potentialField.py
quad_sim_python/quad.py
quad_sim_python/trajectory.py
quad_sim_python/disp/__init__.py
quad_sim_python/disp/animation.py
quad_sim_python-0.0.2.data/scripts/run_online.py
quad_sim_python-0.0.2.data/scripts/run_trajectory.py
quad_sim_python-0.0.2.dist-info/LICENSE
quad_sim_python-0.0.2.dist-info/METADATA
quad_sim_python-0.0.2.dist-info/WHEEL
quad_sim_python-0.0.2.dist-info/top_level.txt
quad_sim_python-0.0.2.dist-info/RECORD
